mcp_datetime/__init__.py
mcp_datetime/__main__.py
mcp_datetime/server.py
mcp_datetime_fastmcp-0.1.5.dist-info/METADATA
mcp_datetime_fastmcp-0.1.5.dist-info/WHEEL
mcp_datetime_fastmcp-0.1.5.dist-info/entry_points.txt
mcp_datetime_fastmcp-0.1.5.dist-info/licenses/LICENSE
mcp_datetime_fastmcp-0.1.5.dist-info/RECORD
