Metadata-Version: 2.4
Name: mcp-datetime-fastmcp
Version: 0.1.5
Summary: A MCP server for datetime formatting and file name generation.
Project-URL: Homepage, https://github.com/fastmcp-me/mcp-datetime#readme
Project-URL: Repository, https://github.com/fastmcp-me/mcp-datetime.git
Project-URL: Issues, https://github.com/fastmcp-me/mcp-datetime/issues
Author-email: ZeparHyfar <zeparhyfar@gmail.com>
License-Expression: MIT
License-File: LICENSE
Keywords: claude,datetime,format,mcp,time,timezone
Classifier: Development Status :: 3 - Alpha
Classifier: Intended Audience :: Developers
Classifier: License :: OSI Approved :: MIT License
Classifier: Programming Language :: Python :: 3
Classifier: Programming Language :: Python :: 3.12
Requires-Python: >=3.12
Requires-Dist: mcp>=1.1.1
Provides-Extra: dev
Requires-Dist: pylint>=3.0.3; extra == 'dev'
Requires-Dist: pytest>=8.0.0; extra == 'dev'
